elektronn/utils.py
elektronn/__init__.py
elektronn/training/warping.py
elektronn/training/trainutils.py
elektronn/training/trainer.py
elektronn/training/traindata.py
elektronn/training/predictor.py
elektronn/training/parallelisation.py
elektronn/training/config.py
elektronn/training/__init__.py
elektronn/training/CNNData.py
elektronn/training/_warping.so
elektronn/net/pooling.py
elektronn/net/perceptronlayer.py
elektronn/net/optimizer.py
elektronn/net/netutils.py
elektronn/net/netcreation.py
elektronn/net/introspection.py
elektronn/net/gaborfilters.py
elektronn/net/convnet.py
elektronn/net/convlayer3d.py
elektronn/net/convlayer2d.py
elektronn/net/__init__.py
elektronn/examples/neuro_3d_config.py
elektronn/examples/config_template.py
elektronn/examples/__init__.py
elektronn/examples/MNIST_MLP_config.py
elektronn/examples/MNIST_Denoising_Autoencoder.py
elektronn/examples/MNIST_CNN_warp_config.py
elektronn/examples/MNIST_CNN_standalone_Dropout.py
elektronn/examples/MNIST_CNN_standalone.py
elektronn-1.0.14.data/scripts/elektronn-train
elektronn-1.0.14.data/scripts/elektronn-profile
elektronn-1.0.14.dist-info/DESCRIPTION.rst
elektronn-1.0.14.dist-info/metadata.json
elektronn-1.0.14.dist-info/top_level.txt
elektronn-1.0.14.dist-info/WHEEL
elektronn-1.0.14.dist-info/METADATA
elektronn-1.0.14.dist-info/RECORD
