Metadata-Version: 2.0
Name: elektronn
Version: 1.0.14
Summary: A highly configurable toolkit for training 3d/2d CNNs and general Neural Networks
Home-page: http://www.elektronn.org/
Author: Marius Killinger, Gregor Urban
Author-email: Marius.Killinger@mailbox.org
License: GPLv3
Keywords: cnn theano convolutional neural network machine learning classification
Platform: UNKNOWN
Classifier: Development Status :: 4 - Beta
Classifier: Environment :: Console
Classifier: Intended Audience :: Science/Research
Classifier: License :: OSI Approved :: GNU General Public License v3 or later (GPLv3+)
Classifier: Operating System :: POSIX :: Linux
Classifier: Programming Language :: Python :: 2 :: Only
Classifier: Programming Language :: Python :: 2.7
Classifier: Topic :: Scientific/Engineering :: Artificial Intelligence
Classifier: Topic :: Scientific/Engineering :: Information Analysis
Requires-Dist: h5py (>=2.2)
Requires-Dist: matplotlib (<2)
Requires-Dist: numpy (>=1.8)
Requires-Dist: scipy (>=0.14)
Requires-Dist: theano (>=0.7)
Provides-Extra: cross-validation
Requires-Dist: scikit-learn (>=0.14,<0.20); extra == 'cross-validation'
